{
  "variants": {
    "state=0": {
      "model": "civilization_fire:block/soybean/soybean_0"
    },
    "state=1": {
      "model": "civilization_fire:block/soybean/soybean_1"
    },
    "state=2": {
      "model": "civilization_fire:block/soybean/soybean_2"
    },
    "state=3": {
      "model": "civilization_fire:block/soybean/soybean_3"
    },
    "state=4": {
      "model": "civilization_fire:block/soybean/soybean_4"
    },
    "state=5": {
      "model": "civilization_fire:block/soybean/soybean_4"
    },
    "state=6": {
      "model": "civilization_fire:block/soybean/soybean_4"
    },
    "state=7": {
      "model": "civilization_fire:block/soybean/soybean_4"
    }
  }
}